tests/install_R.py
tests/__init__.py
tests/utils.py
tests/R/results/test_EI.yaml
tests/R/results/test_homGP_SIR.yaml
tests/R/results/test_hetGP_SIR.yaml
tests/R/results/test_find_reps.yaml
tests/R/results/test_hetGP_mcycle.yaml
tests/R/results/test_allocate_mult.yaml
tests/R/results/test_horizon.yaml
tests/R/results/test_auto_bounds.yaml
tests/R/results/test_homGP_mcycle.yaml
tests/R/results/test_duplicated.yaml
tests/data/hetGP_mcycle_matern52.mat
tests/data/checkGrad.mat
tests/data/mcycle.mat
tests/data/mcycle_Matern52.mat
tests/data/hetGP_mcycle_fit.mat
tests/data/homGP_mcycle.mat
tests/data/homGP_SIR.mat
tests/data/homGP_mcycle_fit.mat
tests/data/mcycle_Gauss_hom_preds.mat
tests/data/hetGP_mcycle.mat
tests/data/f1d.mat
tests/data/mcycle_Matern32.mat
tests/data/SIR.mat
docs/conf.py
hetgpy-1.0.4.dist-info/RECORD
hetgpy-1.0.4.dist-info/WHEEL
hetgpy-1.0.4.dist-info/top_level.txt
hetgpy-1.0.4.dist-info/METADATA
hetgpy-1.0.4.dist-info/licenses/LICENSE
hetgpy/hetGP.py
hetgpy/find_reps.py
hetgpy/plot.py
hetgpy/qEI.cpython-311-darwin.so
hetgpy/update_covar.py
hetgpy/io.py
hetgpy/__init__.py
hetgpy/IMSE.py
hetgpy/utils.py
hetgpy/matern.cpython-311-darwin.so
hetgpy/example_data.py
hetgpy/LOO.py
hetgpy/test_functions.py
hetgpy/homGP.py
hetgpy/EMSE.cpython-311-darwin.so
hetgpy/covariance_functions.py
hetgpy/optim.py
hetgpy/contour.py
hetgpy/auto_bounds.py
hetgpy/src/EMSE.cpp
hetgpy/src/matern.cpp
hetgpy/src/qEI.cpp
