Metadata-Version: 2.4
Name: hetgpy
Version: 1.0.4
Summary: Python implementation of hetGP
Author-email: David O'Gara <david.ogara@wustl.edu>, Mickaël Binois <mickael.binois@inria.fr>
Requires-Python: >3.10
License-File: LICENSE
Requires-Dist: matplotlib>=3.6
Requires-Dist: numpy>=1.20.2
Requires-Dist: scipy>=1.14.0
Requires-Dist: tqdm<5.0.0,>=4.66.4
Requires-Dist: joblib
Provides-Extra: dev
Requires-Dist: dash>=2.14.1; extra == "dev"
Requires-Dist: ipykernel>=6.27.1; extra == "dev"
Requires-Dist: jupyter>=1.0.0; extra == "dev"
Requires-Dist: sphinx>=7.2.6; extra == "dev"
Requires-Dist: numpydoc>=1.6.0; extra == "dev"
Requires-Dist: sphinx-rtd-theme>=2.0.0; extra == "dev"
Requires-Dist: rpy2==3.5.12; extra == "dev"
Requires-Dist: pytest>=7.4.3; extra == "dev"
Requires-Dist: cython>=3.0.6; extra == "dev"
Requires-Dist: pybind11>=2.11.1; extra == "dev"
Requires-Dist: joblib; extra == "dev"
Requires-Dist: pandas; extra == "dev"
Requires-Dist: PyYAML; extra == "dev"
Requires-Dist: nbsphinx>=0.9.5; extra == "dev"
Requires-Dist: jaxtyping>=0.2.19; extra == "dev"
Dynamic: license-file
